notify_online/__init__.py
notify_online/notify_online.py
notify_online-0.1.1.dist-info/LICENSE
notify_online-0.1.1.dist-info/METADATA
notify_online-0.1.1.dist-info/WHEEL
notify_online-0.1.1.dist-info/top_level.txt
notify_online-0.1.1.dist-info/RECORD
