Metadata-Version: 2.1
Name: notify_online
Version: 0.1.1
Summary: A package to send email notifications when the device comes online
Home-page: https://github.com/datlt4
Author: Koi
Author-email: your.email@example.com
Classifier: Programming Language :: Python :: 3
Classifier: License :: OSI Approved :: MIT License
Classifier: Operating System :: OS Independent
Requires-Python: >=3.6
License-File: LICENSE
Requires-Dist: Flask
Requires-Dist: Flask-CORS
Requires-Dist: Flask-Mail
Requires-Dist: Jinja2
Requires-Dist: requests
